m3_learning/__init__.py
m3_learning/RHEED/AFM.py
m3_learning/RHEED/Analysis.py
m3_learning/RHEED/Dataset.py
m3_learning/RHEED/Fit.py
m3_learning/RHEED/Packed_functions.py
m3_learning/RHEED/Viz.py
m3_learning/RHEED/XRD.py
m3_learning/RHEED/__init__.py
m3_learning/be/__init__.py
m3_learning/be/dataset.py
m3_learning/be/filters.py
m3_learning/be/nn.py
m3_learning/be/processing.py
m3_learning/be/util.py
m3_learning/be/viz.py
m3_learning/nn/__init__.py
m3_learning/nn/random.py
m3_learning/nn/Bright_Field_NN/Autoencoder.py
m3_learning/nn/Bright_Field_NN/Dataset.py
m3_learning/nn/Bright_Field_NN/Viz.py
m3_learning/nn/Bright_Field_NN/__init__.py
m3_learning/nn/Regularization/Regularizers.py
m3_learning/nn/Regularization/__init__.py
m3_learning/nn/STEM_AE/Dataset.py
m3_learning/nn/STEM_AE/STEM_AE.py
m3_learning/nn/STEM_AE/Viz.py
m3_learning/nn/STEM_AE/__init__.py
m3_learning/nn/benchmarks/__init__.py
m3_learning/nn/benchmarks/inference.py
m3_learning/nn/time_series_nn/__init__.py
m3_learning/nn/time_series_nn/nn_util.py
m3_learning/optimizers/AdaHessian.py
m3_learning/optimizers/TRPCGOptimizerv2.py
m3_learning/optimizers/__init__.py
m3_learning/util/__init__.py
m3_learning/util/code.py
m3_learning/util/data_generators.py
m3_learning/util/download.py
m3_learning/util/file_IO.py
m3_learning/util/h5_util.py
m3_learning/util/nn.py
m3_learning/util/preprocessing.py
m3_learning/util/rand_util.py
m3_learning/viz/Movies.py
m3_learning/viz/__init__.py
m3_learning/viz/layout.py
m3_learning/viz/nn.py
m3_learning/viz/printing.py
m3_learning/viz/style.py
m3_learning-0.0.24.dist-info/METADATA
m3_learning-0.0.24.dist-info/WHEEL
m3_learning-0.0.24.dist-info/top_level.txt
m3_learning-0.0.24.dist-info/RECORD
