Metadata-Version: 2.1
Name: m3-learning
Version: 0.0.24
Summary: Tutorials, Projects, and datasets from the M3-learning research group
Home-page: https://github.com/jagar2/m3_learning.git
Author: Joshua C. Agar
Author-email: jca92@drexel.edu
License: BSD-3-Clause
Classifier: Programming Language :: Python :: 3
Classifier: License :: OSI Approved :: BSD License
Classifier: Operating System :: OS Independent
Requires-Python: >=3.10
Requires-Dist: pyNSID
Requires-Dist: sidpy
Requires-Dist: py-cpuinfo
Requires-Dist: datafed
Requires-Dist: jupyter-book
Requires-Dist: protobuf ==3.20.3
Requires-Dist: BGlib
Requires-Dist: hyperspy
Requires-Dist: torch
Requires-Dist: torchvision
Requires-Dist: torchaudio
Requires-Dist: tensorflow
Requires-Dist: jupyter
Requires-Dist: autopep8
Requires-Dist: seaborn
Requires-Dist: wget
Requires-Dist: zenodopy
Requires-Dist: pycroscopy
Requires-Dist: scikit-image
Requires-Dist: scikit-learn
Requires-Dist: matplotlib
Requires-Dist: zenodopy ==0.3.0
Requires-Dist: opencv-python
Requires-Dist: imageio ==2.22.3
Requires-Dist: xrayutilities
